[
  {
    "Region": "Guyane",
    "Hamon": 2088.3592,
    "Macron": 8065.3872,
    "Asselineau": 3072.5285,
    "Fillon": 13106.2543,
    "Cheminade": 264.0454,
    "Lasalle": 528.0908,
    "(Mélenchon|Melenchon)": 1824.3138,
    "(Marine Le Pen)": 1368.2353,
    "entity:/m/0h3t838": 288.0495,
    "entity:/m/0f6b18": 336.0578,
    "Poutou": 144.0248,
    "abbreviation": "GF",
    "max": 4,
    "second": 2,
    "third": 3,
    "maxname": "François Fillon",
    "image": "https://github.com/GoogleTrends/visualassets/blob/master/France_left_primaries/hamon.png?raw=true",
    "secondname": "Emmanuel Macron",
    "thirdname": "François Asselineau",
    "title": "Les candidats les plus recherchés",
    "subtitle": "(Dernière mise à jour le 17/03 à 10h)"
  },
  {
    "Region": "Martinique",
    "Hamon": 5211.668,
    "Macron": 10468.1099,
    "Asselineau": 1970.0463,
    "Fillon": 16476.7512,
    "Cheminade": 143.2761,
    "Lasalle": 259.6879,
    "(Mélenchon|Melenchon)": 2274.508,
    "(Marine Le Pen)": 1871.544,
    "entity:/m/0h3t838": 232.8237,
    "entity:/m/0f6b18": 501.4663,
    "Poutou": 134.3213,
    "abbreviation": "MQ",
    "max": 4,
    "second": 2,
    "third": 1,
    "maxname": "François Fillon",
    "image": "https://github.com/GoogleTrends/visualassets/blob/master/France_left_primaries/hamon.png?raw=true",
    "secondname": "Emmanuel Macron",
    "thirdname": "Benoît Hamon",
    "title": "Les candidats les plus recherchés",
    "subtitle": "(Dernière mise à jour le 17/03 à 10h)"
  },
  {
    "Region": "Guadeloupe",
    "Hamon": 4610.622,
    "Macron": 10428.7878,
    "Asselineau": 1380.0501,
    "Fillon": 15894.1,
    "Cheminade": 141.1415,
    "Lasalle": 462.6304,
    "(Mélenchon|Melenchon)": 2124.9635,
    "(Marine Le Pen)": 1858.3629,
    "entity:/m/0h3t838": 133.3003,
    "entity:/m/0f6b18": 399.9009,
    "Poutou": 101.9355,
    "abbreviation": "GP",
    "max": 4,
    "second": 2,
    "third": 1,
    "maxname": "François Fillon",
    "image": "https://github.com/GoogleTrends/visualassets/blob/master/France_left_primaries/hamon.png?raw=true",
    "secondname": "Emmanuel Macron",
    "thirdname": "Benoît Hamon",
    "title": "Les candidats les plus recherchés",
    "subtitle": "(Dernière mise à jour le 17/03 à 10h)"
  },
  {
    "Region": "Mayotte",
    "Hamon": 2056.708,
    "Macron": 8855.2706,
    "Asselineau": 1142.6156,
    "Fillon": 19652.9877,
    "Cheminade": 114.2616,
    "Lasalle": 342.7847,
    "(Mélenchon|Melenchon)": 2570.885,
    "(Marine Le Pen)": 1771.0541,
    "entity:/m/0h3t838": 57.1308,
    "entity:/m/0f6b18": 228.5231,
    "Poutou": 171.3923,
    "abbreviation": "MT",
    "max": 4,
    "second": 2,
    "third": 7,
    "maxname": "François Fillon",
    "image": "https://github.com/GoogleTrends/visualassets/blob/master/France_left_primaries/hamon.png?raw=true",
    "secondname": "Emmanuel Macron",
    "thirdname": "Jean Luc Melenchon",
    "title": "Les candidats les plus recherchés",
    "subtitle": "(Dernière mise à jour le 17/03 à 10h)"
  },
  {
    "Region": "Réunion",
    "Hamon": 2493.8514,
    "Macron": 10948.3051,
    "Asselineau": 2366.3973,
    "Fillon": 12201.6035,
    "Cheminade": 76.4724,
    "Lasalle": 943.1602,
    "(Mélenchon|Melenchon)": 3216.0912,
    "(Marine Le Pen)": 1920.3081,
    "entity:/m/0h3t838": 186.9326,
    "entity:/m/0f6b18": 369.6168,
    "Poutou": 93.4663,
    "abbreviation": "RE",
    "max": 4,
    "second": 2,
    "third": 7,
    "maxname": "François Fillon",
    "image": "https://github.com/GoogleTrends/visualassets/blob/master/France_left_primaries/hamon.png?raw=true",
    "secondname": "Emmanuel Macron",
    "thirdname": "Jean Luc Melenchon",
    "title": "Les candidats les plus recherchés",
    "subtitle": "(Dernière mise à jour le 17/03 à 10h)"
  },
  {
    "Region": "Auvergne-Rhône-Alpes",
    "Hamon": 3559.1544,
    "Macron": 15550.1556,
    "Asselineau": 2719.035,
    "Fillon": 16798.9817,
    "Cheminade": 304.2595,
    "Lasalle": 515.4246,
    "(Mélenchon|Melenchon)": 3824.5299,
    "(Marine Le Pen)": 2637.8613,
    "entity:/m/0h3t838": 470.2966,
    "entity:/m/0f6b18": 997.0741,
    "Poutou": 458.0921,
    "abbreviation": "AR",
    "max": 4,
    "second": 2,
    "third": 7,
    "maxname": "François Fillon",
    "image": "https://github.com/GoogleTrends/visualassets/blob/master/France_left_primaries/hamon.png?raw=true",
    "secondname": "Emmanuel Macron",
    "thirdname": "Jean Luc Melenchon",
    "title": "Les candidats les plus recherchés",
    "subtitle": "(Dernière mise à jour le 17/03 à 10h)"
  },
  {
    "Region": "Bourgogne-Franche-Comté",
    "Hamon": 3275.8364,
    "Macron": 14232.9809,
    "Asselineau": 2725.2846,
    "Fillon": 16504.9319,
    "Cheminade": 379.363,
    "Lasalle": 571.6863,
    "(Mélenchon|Melenchon)": 3954.2516,
    "(Marine Le Pen)": 2792.9147,
    "entity:/m/0h3t838": 509.3397,
    "entity:/m/0f6b18": 1018.6795,
    "Poutou": 354.0017,
    "abbreviation": "BF",
    "max": 4,
    "second": 2,
    "third": 7,
    "maxname": "François Fillon",
    "image": "https://github.com/GoogleTrends/visualassets/blob/master/France_left_primaries/hamon.png?raw=true",
    "secondname": "Emmanuel Macron",
    "thirdname": "Jean Luc Melenchon",
    "title": "Les candidats les plus recherchés",
    "subtitle": "(Dernière mise à jour le 17/03 à 10h)"
  },
  {
    "Region": "Bretagne",
    "Hamon": 5314.0544,
    "Macron": 17517.6403,
    "Asselineau": 2850.2024,
    "Fillon": 20922.3058,
    "Cheminade": 336.9963,
    "Lasalle": 636.9771,
    "(Mélenchon|Melenchon)": 4451.899,
    "(Marine Le Pen)": 2783.8828,
    "entity:/m/0h3t838": 554.4631,
    "entity:/m/0f6b18": 1030.268,
    "Poutou": 467.3222,
    "abbreviation": "BT",
    "max": 4,
    "second": 2,
    "third": 1,
    "maxname": "François Fillon",
    "image": "https://github.com/GoogleTrends/visualassets/blob/master/France_left_primaries/hamon.png?raw=true",
    "secondname": "Emmanuel Macron",
    "thirdname": "Benoît Hamon",
    "title": "Les candidats les plus recherchés",
    "subtitle": "(Dernière mise à jour le 17/03 à 10h)"
  },
  {
    "Region": "Centre-Val de Loire",
    "Hamon": 3207.5341,
    "Macron": 14683.9712,
    "Asselineau": 2820.7629,
    "Fillon": 16545.5858,
    "Cheminade": 343.4262,
    "Lasalle": 479.0184,
    "(Mélenchon|Melenchon)": 3598.751,
    "(Marine Le Pen)": 3428.7051,
    "entity:/m/0h3t838": 516.8064,
    "entity:/m/0f6b18": 1078.0693,
    "Poutou": 366.7659,
    "abbreviation": "CV",
    "max": 4,
    "second": 2,
    "third": 7,
    "maxname": "François Fillon",
    "image": "https://github.com/GoogleTrends/visualassets/blob/master/France_left_primaries/hamon.png?raw=true",
    "secondname": "Emmanuel Macron",
    "thirdname": "Jean Luc Melenchon",
    "title": "Les candidats les plus recherchés",
    "subtitle": "(Dernière mise à jour le 17/03 à 10h)"
  },
  {
    "Region": "Corse",
    "Hamon": 3049.1656,
    "Macron": 15462.9206,
    "Asselineau": 2476.8303,
    "Fillon": 21511.9125,
    "Cheminade": 345.3747,
    "Lasalle": 552.5996,
    "(Mélenchon|Melenchon)": 3276.1261,
    "(Marine Le Pen)": 3473.4831,
    "entity:/m/0h3t838": 394.714,
    "entity:/m/0f6b18": 1134.8027,
    "Poutou": 522.996,
    "abbreviation": "CE",
    "max": 4,
    "second": 2,
    "third": 8,
    "maxname": "François Fillon",
    "image": "https://github.com/GoogleTrends/visualassets/blob/master/France_left_primaries/hamon.png?raw=true",
    "secondname": "Emmanuel Macron",
    "thirdname": "Marine Le Pen",
    "title": "Les candidats les plus recherchés",
    "subtitle": "(Dernière mise à jour le 17/03 à 10h)"
  },
  {
    "Region": "Grand Est",
    "Hamon": 2857.279,
    "Macron": 13122.0266,
    "Asselineau": 2547.2401,
    "Fillon": 14656.473,
    "Cheminade": 351.3774,
    "Lasalle": 596.9479,
    "(Mélenchon|Melenchon)": 3162.3966,
    "(Marine Le Pen)": 2693.8934,
    "entity:/m/0h3t838": 434.5466,
    "entity:/m/0f6b18": 995.5693,
    "Poutou": 311.5153,
    "abbreviation": "GE",
    "max": 4,
    "second": 2,
    "third": 7,
    "maxname": "François Fillon",
    "image": "https://github.com/GoogleTrends/visualassets/blob/master/France_left_primaries/hamon.png?raw=true",
    "secondname": "Emmanuel Macron",
    "thirdname": "Jean Luc Melenchon",
    "title": "Les candidats les plus recherchés",
    "subtitle": "(Dernière mise à jour le 17/03 à 10h)"
  },
  {
    "Region": "Hauts-de-France",
    "Hamon": 2748.1173,
    "Macron": 12821.5774,
    "Asselineau": 2080.3546,
    "Fillon": 12879.0433,
    "Cheminade": 258.8193,
    "Lasalle": 981.8205,
    "(Mélenchon|Melenchon)": 3036.7832,
    "(Marine Le Pen)": 2433.614,
    "entity:/m/0h3t838": 385.7788,
    "entity:/m/0f6b18": 800.0679,
    "Poutou": 302.4755,
    "abbreviation": "HF",
    "max": 4,
    "second": 2,
    "third": 7,
    "maxname": "François Fillon",
    "image": "https://github.com/GoogleTrends/visualassets/blob/master/France_left_primaries/hamon.png?raw=true",
    "secondname": "Emmanuel Macron",
    "thirdname": "Jean Luc Melenchon",
    "title": "Les candidats les plus recherchés",
    "subtitle": "(Dernière mise à jour le 17/03 à 10h)"
  },
  {
    "Region": "Île-de-France",
    "Hamon": 4777.4153,
    "Macron": 19144.925,
    "Asselineau": 3367.3741,
    "Fillon": 21400.3865,
    "Cheminade": 368.253,
    "Lasalle": 361.5025,
    "(Mélenchon|Melenchon)": 4039.0958,
    "(Marine Le Pen)": 2721.0422,
    "entity:/m/0h3t838": 488.4516,
    "entity:/m/0f6b18": 993.5275,
    "Poutou": 536.4101,
    "abbreviation": "IF",
    "max": 4,
    "second": 2,
    "third": 1,
    "maxname": "François Fillon",
    "image": "https://github.com/GoogleTrends/visualassets/blob/master/France_left_primaries/hamon.png?raw=true",
    "secondname": "Emmanuel Macron",
    "thirdname": "Benoît Hamon",
    "title": "Les candidats les plus recherchés",
    "subtitle": "(Dernière mise à jour le 17/03 à 10h)"
  },
  {
    "Region": "Nouvelle-Aquitaine",
    "Hamon": 3667.7107,
    "Macron": 16544.0267,
    "Asselineau": 2793.6466,
    "Fillon": 17950.1297,
    "Cheminade": 355.2819,
    "Lasalle": 435.2645,
    "(Mélenchon|Melenchon)": 3980.5709,
    "(Marine Le Pen)": 2575.7935,
    "entity:/m/0h3t838": 505.0835,
    "entity:/m/0f6b18": 1053.4726,
    "Poutou": 527.1782,
    "abbreviation": "NQ",
    "max": 4,
    "second": 2,
    "third": 7,
    "maxname": "François Fillon",
    "image": "https://github.com/GoogleTrends/visualassets/blob/master/France_left_primaries/hamon.png?raw=true",
    "secondname": "Emmanuel Macron",
    "thirdname": "Jean Luc Melenchon",
    "title": "Les candidats les plus recherchés",
    "subtitle": "(Dernière mise à jour le 17/03 à 10h)"
  },
  {
    "Region": "Pays de la Loire",
    "Hamon": 4229.2986,
    "Macron": 15857.9781,
    "Asselineau": 2670.0499,
    "Fillon": 20322.5052,
    "Cheminade": 326.7063,
    "Lasalle": 674.0466,
    "(Mélenchon|Melenchon)": 3521.5496,
    "(Marine Le Pen)": 2551.7479,
    "entity:/m/0h3t838": 522.73,
    "entity:/m/0f6b18": 1014.5089,
    "Poutou": 400.9889,
    "abbreviation": "PL",
    "max": 4,
    "second": 2,
    "third": 1,
    "maxname": "François Fillon",
    "image": "https://github.com/GoogleTrends/visualassets/blob/master/France_left_primaries/hamon.png?raw=true",
    "secondname": "Emmanuel Macron",
    "thirdname": "Benoît Hamon",
    "title": "Les candidats les plus recherchés",
    "subtitle": "(Dernière mise à jour le 17/03 à 10h)"
  },
  {
    "Region": "PACA",
    "Hamon": 3335.1519,
    "Macron": 16085.6022,
    "Asselineau": 2515.8075,
    "Fillon": 17568.6347,
    "Cheminade": 305.583,
    "Lasalle": 504.6894,
    "(Mélenchon|Melenchon)": 3740.5268,
    "(Marine Le Pen)": 3559.0869,
    "entity:/m/0h3t838": 392.0057,
    "entity:/m/0f6b18": 999.3519,
    "Poutou": 336.6188,
    "abbreviation": "PR",
    "max": 4,
    "second": 2,
    "third": 7,
    "maxname": "François Fillon",
    "image": "https://github.com/GoogleTrends/visualassets/blob/master/France_left_primaries/hamon.png?raw=true",
    "secondname": "Emmanuel Macron",
    "thirdname": "Jean Luc Melenchon",
    "title": "Les candidats les plus recherchés",
    "subtitle": "(Dernière mise à jour le 17/03 à 10h)"
  },
  {
    "Region": "Normandie",
    "Hamon": 3854.1874,
    "Macron": 14522.6053,
    "Asselineau": 2443.1426,
    "Fillon": 17624.0084,
    "Cheminade": 314.2278,
    "Lasalle": 631.8619,
    "(Mélenchon|Melenchon)": 3727.3041,
    "(Marine Le Pen)": 2747.1517,
    "entity:/m/0h3t838": 539.0412,
    "entity:/m/0f6b18": 994.629,
    "Poutou": 396.8297,
    "abbreviation": "NO",
    "max": 4,
    "second": 2,
    "third": 1,
    "maxname": "François Fillon",
    "image": "https://github.com/GoogleTrends/visualassets/blob/master/France_left_primaries/hamon.png?raw=true",
    "secondname": "Emmanuel Macron",
    "thirdname": "Benoît Hamon",
    "title": "Les candidats les plus recherchés",
    "subtitle": "(Dernière mise à jour le 17/03 à 10h)"
  },
  {
    "Region": "Occitanie",
    "Hamon": 3820.0716,
    "Macron": 15909.6765,
    "Asselineau": 2717.0039,
    "Fillon": 16647.7795,
    "Cheminade": 314.6951,
    "Lasalle": 652.2771,
    "(Mélenchon|Melenchon)": 4692.6353,
    "(Marine Le Pen)": 2885.7949,
    "entity:/m/0h3t838": 459.3731,
    "entity:/m/0f6b18": 1003.7548,
    "Poutou": 424.634,
    "abbreviation": "OC",
    "max": 4,
    "second": 2,
    "third": 7,
    "maxname": "François Fillon",
    "image": "https://github.com/GoogleTrends/visualassets/blob/master/France_left_primaries/hamon.png?raw=true",
    "secondname": "Emmanuel Macron",
    "thirdname": "Jean Luc Melenchon",
    "title": "Les candidats les plus recherchés",
    "subtitle": "(Dernière mise à jour le 17/03 à 10h)"
  },
  {
    "Region": "Auvergne-Rhône-Alpes",
    "Hamon": 3559.1544,
    "Macron": 15550.1556,
    "Asselineau": 2719.035,
    "Fillon": 16798.9817,
    "Cheminade": 304.2595,
    "Lasalle": 515.4246,
    "(Mélenchon|Melenchon)": 3824.5299,
    "(Marine Le Pen)": 2637.8613,
    "entity:/m/0h3t838": 470.2966,
    "entity:/m/0f6b18": 997.0741,
    "Poutou": 458.0921,
    "abbreviation": "AR",
    "max": 4,
    "second": 2,
    "third": 7,
    "maxname": "François Fillon",
    "image": "https://github.com/GoogleTrends/visualassets/blob/master/France_left_primaries/hamon.png?raw=true",
    "secondname": "Emmanuel Macron",
    "thirdname": "Jean Luc Melenchon",
    "title": "Les candidats les plus recherchés",
    "subtitle": "(Dernière mise à jour le 17/03 à 10h)"
  }
]
