[
  {
    "Region": "Guyane",
    "Hamon": 2383.4671,
    "Valls": 560.8158,
    "Melenchon": 1098.2643,
    "abbreviation": "GF",
    "max": 1,
    "second": 3,
    "third": 2,
    "maxname": "Benoît Hamon",
    "image": "https://github.com/GoogleTrends/visualassets/blob/master/France_left_primaries/hamon.png?raw=true",
    "secondname": "Jean-Luc Melenchon",
    "thirdname": "Manuel Valls"
  },
  {
    "Region": "Martinique",
    "Hamon": 5106.5646,
    "Valls": 743.25,
    "Melenchon": 769.4823,
    "abbreviation": "MQ",
    "max": 1,
    "second": 3,
    "third": 2,
    "maxname": "Benoît Hamon",
    "image": "https://github.com/GoogleTrends/visualassets/blob/master/France_left_primaries/hamon.png?raw=true",
    "secondname": "Jean-Luc Melenchon",
    "thirdname": "Manuel Valls"
  },
  {
    "Region": "Guadeloupe",
    "Hamon": 4809.5209,
    "Valls": 685.9855,
    "Melenchon": 899.4033,
    "abbreviation": "GP",
    "max": 1,
    "second": 3,
    "third": 2,
    "maxname": "Benoît Hamon",
    "image": "https://github.com/GoogleTrends/visualassets/blob/master/France_left_primaries/hamon.png?raw=true",
    "secondname": "Jean-Luc Melenchon",
    "thirdname": "Manuel Valls"
  },
  {
    "Region": "Mayotte",
    "Hamon": 2218.6747,
    "Valls": 162.3421,
    "Melenchon": 757.5963,
    "abbreviation": "MT",
    "max": 1,
    "second": 3,
    "third": 2,
    "maxname": "Benoît Hamon",
    "image": "https://github.com/GoogleTrends/visualassets/blob/master/France_left_primaries/hamon.png?raw=true",
    "secondname": "Jean-Luc Melenchon",
    "thirdname": "Manuel Valls"
  },
  {
    "Region": "Réunion",
    "Hamon": 2208.5009,
    "Valls": 414.0939,
    "Melenchon": 1522.5271,
    "abbreviation": "RE",
    "max": 1,
    "second": 3,
    "third": 2,
    "maxname": "Benoît Hamon",
    "image": "https://github.com/GoogleTrends/visualassets/blob/master/France_left_primaries/hamon.png?raw=true",
    "secondname": "Jean-Luc Melenchon",
    "thirdname": "Manuel Valls"
  },
  {
    "Region": "Auvergne-Rhône-Alpes",
    "Hamon": 4120.989,
    "Valls": 705.4396,
    "Melenchon": 1442.8183,
    "abbreviation": "AR",
    "max": 1,
    "second": 3,
    "third": 2,
    "maxname": "Benoît Hamon",
    "image": "https://github.com/GoogleTrends/visualassets/blob/master/France_left_primaries/hamon.png?raw=true",
    "secondname": "Jean-Luc Melenchon",
    "thirdname": "Manuel Valls"
  },
  {
    "Region": "Bourgogne-Franche-Comté",
    "Hamon": 3728.2947,
    "Valls": 641.8901,
    "Melenchon": 1473.4762,
    "abbreviation": "BF",
    "max": 1,
    "second": 3,
    "third": 2,
    "maxname": "Benoît Hamon",
    "image": "https://github.com/GoogleTrends/visualassets/blob/master/France_left_primaries/hamon.png?raw=true",
    "secondname": "Jean-Luc Melenchon",
    "thirdname": "Manuel Valls"
  },
  {
    "Region": "Bretagne",
    "Hamon": 6063.9575,
    "Valls": 827.9678,
    "Melenchon": 1588.701,
    "abbreviation": "BT",
    "max": 1,
    "second": 3,
    "third": 2,
    "maxname": "Benoît Hamon",
    "image": "https://github.com/GoogleTrends/visualassets/blob/master/France_left_primaries/hamon.png?raw=true",
    "secondname": "Jean-Luc Melenchon",
    "thirdname": "Manuel Valls"
  },
  {
    "Region": "Centre-Val de Loire",
    "Hamon": 3672.8717,
    "Valls": 656.0636,
    "Melenchon": 1162.4796,
    "abbreviation": "CV",
    "max": 1,
    "second": 3,
    "third": 2,
    "maxname": "Benoît Hamon",
    "image": "https://github.com/GoogleTrends/visualassets/blob/master/France_left_primaries/hamon.png?raw=true",
    "secondname": "Jean-Luc Melenchon",
    "thirdname": "Manuel Valls"
  },
  {
    "Region": "Corse",
    "Hamon": 3824.4906,
    "Valls": 656.7307,
    "Melenchon": 1390.7239,
    "abbreviation": "CE",
    "max": 1,
    "second": 3,
    "third": 2,
    "maxname": "Benoît Hamon",
    "image": "https://github.com/GoogleTrends/visualassets/blob/master/France_left_primaries/hamon.png?raw=true",
    "secondname": "Jean-Luc Melenchon",
    "thirdname": "Manuel Valls"
  },
  {
    "Region": "Grand Est",
    "Hamon": 3205.4394,
    "Valls": 571.4273,
    "Melenchon": 1108.932,
    "abbreviation": "GE",
    "max": 1,
    "second": 3,
    "third": 2,
    "maxname": "Benoît Hamon",
    "image": "https://github.com/GoogleTrends/visualassets/blob/master/France_left_primaries/hamon.png?raw=true",
    "secondname": "Jean-Luc Melenchon",
    "thirdname": "Manuel Valls"
  },
  {
    "Region": "Hauts-de-France",
    "Hamon": 3006.7226,
    "Valls": 610.4361,
    "Melenchon": 1088.3946,
    "abbreviation": "HF",
    "max": 1,
    "second": 3,
    "third": 2,
    "maxname": "Benoît Hamon",
    "image": "https://github.com/GoogleTrends/visualassets/blob/master/France_left_primaries/hamon.png?raw=true",
    "secondname": "Jean-Luc Melenchon",
    "thirdname": "Manuel Valls"
  },
  {
    "Region": "Île-de-France",
    "Hamon": 5406.0754,
    "Valls": 1171.3889,
    "Melenchon": 1569.477,
    "abbreviation": "IF",
    "max": 1,
    "second": 3,
    "third": 2,
    "maxname": "Benoît Hamon",
    "image": "https://github.com/GoogleTrends/visualassets/blob/master/France_left_primaries/hamon.png?raw=true",
    "secondname": "Jean-Luc Melenchon",
    "thirdname": "Manuel Valls"
  },
  {
    "Region": "Nouvelle-Aquitaine",
    "Hamon": 4309.4448,
    "Valls": 714.9889,
    "Melenchon": 1545.7461,
    "abbreviation": "NQ",
    "max": 1,
    "second": 3,
    "third": 2,
    "maxname": "Benoît Hamon",
    "image": "https://github.com/GoogleTrends/visualassets/blob/master/France_left_primaries/hamon.png?raw=true",
    "secondname": "Jean-Luc Melenchon",
    "thirdname": "Manuel Valls"
  },
  {
    "Region": "Pays de la Loire",
    "Hamon": 4899.9322,
    "Valls": 629.7992,
    "Melenchon": 1275.7299,
    "abbreviation": "PL",
    "max": 1,
    "second": 3,
    "third": 2,
    "maxname": "Benoît Hamon",
    "image": "https://github.com/GoogleTrends/visualassets/blob/master/France_left_primaries/hamon.png?raw=true",
    "secondname": "Jean-Luc Melenchon",
    "thirdname": "Manuel Valls"
  },
  {
    "Region": "PACA",
    "Hamon": 3679.6093,
    "Valls": 704.606,
    "Melenchon": 1477.1259,
    "abbreviation": "PR",
    "max": 1,
    "second": 3,
    "third": 2,
    "maxname": "Benoît Hamon",
    "image": "https://github.com/GoogleTrends/visualassets/blob/master/France_left_primaries/hamon.png?raw=true",
    "secondname": "Jean-Luc Melenchon",
    "thirdname": "Manuel Valls"
  },
  {
    "Region": "Normandie",
    "Hamon": 4448.9649,
    "Valls": 620.7665,
    "Melenchon": 1295.4046,
    "abbreviation": "NO",
    "max": 1,
    "second": 3,
    "third": 2,
    "maxname": "Benoît Hamon",
    "image": "https://github.com/GoogleTrends/visualassets/blob/master/France_left_primaries/hamon.png?raw=true",
    "secondname": "Jean-Luc Melenchon",
    "thirdname": "Manuel Valls"
  },
  {
    "Region": "Occitanie",
    "Hamon": 4390.2437,
    "Valls": 819.9179,
    "Melenchon": 1796.7731,
    "abbreviation": "OC",
    "max": 1,
    "second": 3,
    "third": 2,
    "maxname": "Benoît Hamon",
    "image": "https://github.com/GoogleTrends/visualassets/blob/master/France_left_primaries/hamon.png?raw=true",
    "secondname": "Jean-Luc Melenchon",
    "thirdname": "Manuel Valls"
  },
  {
    "Region": "Auvergne-Rhône-Alpes",
    "Hamon": 4120.989,
    "Valls": 705.4396,
    "Melenchon": 1442.8183,
    "abbreviation": "AR",
    "max": 1,
    "second": 3,
    "third": 2,
    "maxname": "Benoît Hamon",
    "image": "https://github.com/GoogleTrends/visualassets/blob/master/France_left_primaries/hamon.png?raw=true",
    "secondname": "Jean-Luc Melenchon",
    "thirdname": "Manuel Valls"
  }
]
