[
  {
    "Region": "Guyane",
    "Hamon": 2290.3714,
    "Macron": 7944.7257,
    "Asselineau": 3196.9767,
    "Fillon": 12859.4809,
    "Cheminade": 262.4384,
    "Lasalle": 501.0187,
    "(Mélenchon|Melenchon)": 1741.6366,
    "(Marine Le Pen)": 1503.0562,
    "entity:/m/0h3t838": 262.4384,
    "entity:/m/0f6b18": 357.8705,
    "Poutou": 143.1482,
    "abbreviation": "GF",
    "max": 4,
    "second": 2,
    "third": 3,
    "maxname": "François Fillon",
    "image": "https://github.com/GoogleTrends/visualassets/blob/master/France_left_primaries/hamon.png?raw=true",
    "secondname": "Emmanuel Macron",
    "thirdname": "François Asselineau",
    "title": "Les candidats les plus recherchés",
    "subtitle": "(Dernière mise à jour le 16/03 à 22h)"
  },
  {
    "Region": "Martinique",
    "Hamon": 5295.7192,
    "Macron": 10778.3461,
    "Asselineau": 1993.6825,
    "Fillon": 16136.3679,
    "Cheminade": 133.5055,
    "Lasalle": 258.1107,
    "(Mélenchon|Melenchon)": 2242.8928,
    "(Marine Le Pen)": 1940.2803,
    "entity:/m/0h3t838": 222.5092,
    "entity:/m/0f6b18": 516.2214,
    "Poutou": 151.3063,
    "abbreviation": "MQ",
    "max": 4,
    "second": 2,
    "third": 1,
    "maxname": "François Fillon",
    "image": "https://github.com/GoogleTrends/visualassets/blob/master/France_left_primaries/hamon.png?raw=true",
    "secondname": "Emmanuel Macron",
    "thirdname": "Benoît Hamon",
    "title": "Les candidats les plus recherchés",
    "subtitle": "(Dernière mise à jour le 16/03 à 22h)"
  },
  {
    "Region": "Guadeloupe",
    "Hamon": 4876.9851,
    "Macron": 10621.5108,
    "Asselineau": 1391.1913,
    "Fillon": 15834.5702,
    "Cheminade": 140.6823,
    "Lasalle": 461.1252,
    "(Mélenchon|Melenchon)": 2055.5242,
    "(Marine Le Pen)": 1899.2105,
    "entity:/m/0h3t838": 156.3136,
    "entity:/m/0f6b18": 414.2311,
    "Poutou": 140.6823,
    "abbreviation": "GP",
    "max": 4,
    "second": 2,
    "third": 1,
    "maxname": "François Fillon",
    "image": "https://github.com/GoogleTrends/visualassets/blob/master/France_left_primaries/hamon.png?raw=true",
    "secondname": "Emmanuel Macron",
    "thirdname": "Benoît Hamon",
    "title": "Les candidats les plus recherchés",
    "subtitle": "(Dernière mise à jour le 16/03 à 22h)"
  },
  {
    "Region": "Mayotte",
    "Hamon": 2184.874,
    "Macron": 8907.563,
    "Asselineau": 1176.4706,
    "Fillon": 19383.7535,
    "Cheminade": 112.0448,
    "Lasalle": 336.1345,
    "(Mélenchon|Melenchon)": 2689.0756,
    "(Marine Le Pen)": 1680.6723,
    "entity:/m/0h3t838": 56.0224,
    "entity:/m/0f6b18": 224.0896,
    "Poutou": 168.0672,
    "abbreviation": "MT",
    "max": 4,
    "second": 2,
    "third": 7,
    "maxname": "François Fillon",
    "image": "https://github.com/GoogleTrends/visualassets/blob/master/France_left_primaries/hamon.png?raw=true",
    "secondname": "Emmanuel Macron",
    "thirdname": "Jean Luc Melenchon",
    "title": "Les candidats les plus recherchés",
    "subtitle": "(Dernière mise à jour le 16/03 à 22h)"
  },
  {
    "Region": "Réunion",
    "Hamon": 2494.4537,
    "Macron": 10962.1356,
    "Asselineau": 2284.1288,
    "Fillon": 12030.5863,
    "Cheminade": 75.717,
    "Lasalle": 971.7012,
    "(Mélenchon|Melenchon)": 3209.5585,
    "(Marine Le Pen)": 1930.7829,
    "entity:/m/0h3t838": 180.8794,
    "entity:/m/0f6b18": 361.7589,
    "Poutou": 92.543,
    "abbreviation": "RE",
    "max": 4,
    "second": 2,
    "third": 7,
    "maxname": "François Fillon",
    "image": "https://github.com/GoogleTrends/visualassets/blob/master/France_left_primaries/hamon.png?raw=true",
    "secondname": "Emmanuel Macron",
    "thirdname": "Jean Luc Melenchon",
    "title": "Les candidats les plus recherchés",
    "subtitle": "(Dernière mise à jour le 16/03 à 22h)"
  },
  {
    "Region": "Auvergne-Rhône-Alpes",
    "Hamon": 3932.2371,
    "Macron": 15708.7918,
    "Asselineau": 2719.7192,
    "Fillon": 16708.1041,
    "Cheminade": 299.7937,
    "Lasalle": 514.4187,
    "(Mélenchon|Melenchon)": 3735.2136,
    "(Marine Le Pen)": 2626.8854,
    "entity:/m/0h3t838": 467.5759,
    "entity:/m/0f6b18": 989.0921,
    "Poutou": 442.0254,
    "abbreviation": "AR",
    "max": 4,
    "second": 2,
    "third": 1,
    "maxname": "François Fillon",
    "image": "https://github.com/GoogleTrends/visualassets/blob/master/France_left_primaries/hamon.png?raw=true",
    "secondname": "Emmanuel Macron",
    "thirdname": "Benoît Hamon",
    "title": "Les candidats les plus recherchés",
    "subtitle": "(Dernière mise à jour le 16/03 à 22h)"
  },
  {
    "Region": "Bourgogne-Franche-Comté",
    "Hamon": 3589.4642,
    "Macron": 14385.3299,
    "Asselineau": 2720.8921,
    "Fillon": 16540.9104,
    "Cheminade": 374.0566,
    "Lasalle": 577.9914,
    "(Mélenchon|Melenchon)": 3844.1186,
    "(Marine Le Pen)": 2815.9912,
    "entity:/m/0h3t838": 507.1954,
    "entity:/m/0f6b18": 1028.1274,
    "Poutou": 339.1869,
    "abbreviation": "BF",
    "max": 4,
    "second": 2,
    "third": 7,
    "maxname": "François Fillon",
    "image": "https://github.com/GoogleTrends/visualassets/blob/master/France_left_primaries/hamon.png?raw=true",
    "secondname": "Emmanuel Macron",
    "thirdname": "Jean Luc Melenchon",
    "title": "Les candidats les plus recherchés",
    "subtitle": "(Dernière mise à jour le 16/03 à 22h)"
  },
  {
    "Region": "Bretagne",
    "Hamon": 5787.3218,
    "Macron": 17703.6209,
    "Asselineau": 2852.0144,
    "Fillon": 20731.4761,
    "Cheminade": 333.9433,
    "Lasalle": 632.4099,
    "(Mélenchon|Melenchon)": 4346.6612,
    "(Marine Le Pen)": 2777.2049,
    "entity:/m/0h3t838": 546.032,
    "entity:/m/0f6b18": 1010.3134,
    "Poutou": 448.0855,
    "abbreviation": "BT",
    "max": 4,
    "second": 2,
    "third": 1,
    "maxname": "François Fillon",
    "image": "https://github.com/GoogleTrends/visualassets/blob/master/France_left_primaries/hamon.png?raw=true",
    "secondname": "Emmanuel Macron",
    "thirdname": "Benoît Hamon",
    "title": "Les candidats les plus recherchés",
    "subtitle": "(Dernière mise à jour le 16/03 à 22h)"
  },
  {
    "Region": "Centre-Val de Loire",
    "Hamon": 3473.2587,
    "Macron": 14796.9272,
    "Asselineau": 2850.6515,
    "Fillon": 16401.2526,
    "Cheminade": 343.5458,
    "Lasalle": 478.0734,
    "(Mélenchon|Melenchon)": 3479.9295,
    "(Marine Le Pen)": 3432.1222,
    "entity:/m/0h3t838": 518.0981,
    "entity:/m/0f6b18": 1078.4446,
    "Poutou": 353.5519,
    "abbreviation": "CV",
    "max": 4,
    "second": 2,
    "third": 7,
    "maxname": "François Fillon",
    "image": "https://github.com/GoogleTrends/visualassets/blob/master/France_left_primaries/hamon.png?raw=true",
    "secondname": "Emmanuel Macron",
    "thirdname": "Jean Luc Melenchon",
    "title": "Les candidats les plus recherchés",
    "subtitle": "(Dernière mise à jour le 16/03 à 22h)"
  },
  {
    "Region": "Corse",
    "Hamon": 3372.4226,
    "Macron": 15731.4175,
    "Asselineau": 2477.6983,
    "Fillon": 21217.7494,
    "Cheminade": 324.4605,
    "Lasalle": 550.5996,
    "(Mélenchon|Melenchon)": 3057.7943,
    "(Marine Le Pen)": 3451.0797,
    "entity:/m/0h3t838": 393.2854,
    "entity:/m/0f6b18": 1101.1992,
    "Poutou": 491.6068,
    "abbreviation": "CE",
    "max": 4,
    "second": 2,
    "third": 8,
    "maxname": "François Fillon",
    "image": "https://github.com/GoogleTrends/visualassets/blob/master/France_left_primaries/hamon.png?raw=true",
    "secondname": "Emmanuel Macron",
    "thirdname": "Marine Le Pen",
    "title": "Les candidats les plus recherchés",
    "subtitle": "(Dernière mise à jour le 16/03 à 22h)"
  },
  {
    "Region": "Grand Est",
    "Hamon": 3124.6605,
    "Macron": 13189.5117,
    "Asselineau": 2565.174,
    "Fillon": 14566.3306,
    "Cheminade": 347.8953,
    "Lasalle": 590.487,
    "(Mélenchon|Melenchon)": 3075.9453,
    "(Marine Le Pen)": 2674.4141,
    "entity:/m/0h3t838": 427.1189,
    "entity:/m/0f6b18": 983.1609,
    "Poutou": 298.688,
    "abbreviation": "GE",
    "max": 4,
    "second": 2,
    "third": 1,
    "maxname": "François Fillon",
    "image": "https://github.com/GoogleTrends/visualassets/blob/master/France_left_primaries/hamon.png?raw=true",
    "secondname": "Emmanuel Macron",
    "thirdname": "Benoît Hamon",
    "title": "Les candidats les plus recherchés",
    "subtitle": "(Dernière mise à jour le 16/03 à 22h)"
  },
  {
    "Region": "Hauts-de-France",
    "Hamon": 2958.8246,
    "Macron": 12934.6086,
    "Asselineau": 2072.0684,
    "Fillon": 12772.4079,
    "Cheminade": 255.7779,
    "Lasalle": 986.1263,
    "(Mélenchon|Melenchon)": 2937.4355,
    "(Marine Le Pen)": 2449.0512,
    "entity:/m/0h3t838": 385.8949,
    "entity:/m/0f6b18": 794.0701,
    "Poutou": 291.4264,
    "abbreviation": "HF",
    "max": 2,
    "second": 4,
    "third": 1,
    "maxname": "Emmanuel Macron",
    "image": "https://github.com/GoogleTrends/visualassets/blob/master/France_left_primaries/hamon.png?raw=true",
    "secondname": "François Fillon",
    "thirdname": "Benoît Hamon",
    "title": "Les candidats les plus recherchés",
    "subtitle": "(Dernière mise à jour le 16/03 à 22h)"
  },
  {
    "Region": "Île-de-France",
    "Hamon": 5220.2108,
    "Macron": 19302.153,
    "Asselineau": 3374.6797,
    "Fillon": 21196.521,
    "Cheminade": 358.2715,
    "Lasalle": 360.3861,
    "(Mélenchon|Melenchon)": 3911.6842,
    "(Marine Le Pen)": 2721.373,
    "entity:/m/0h3t838": 484.8446,
    "entity:/m/0f6b18": 992.4462,
    "Poutou": 513.744,
    "abbreviation": "IF",
    "max": 4,
    "second": 2,
    "third": 1,
    "maxname": "François Fillon",
    "image": "https://github.com/GoogleTrends/visualassets/blob/master/France_left_primaries/hamon.png?raw=true",
    "secondname": "Emmanuel Macron",
    "thirdname": "Benoît Hamon",
    "title": "Les candidats les plus recherchés",
    "subtitle": "(Dernière mise à jour le 16/03 à 22h)"
  },
  {
    "Region": "Nouvelle-Aquitaine",
    "Hamon": 4084.146,
    "Macron": 16871.5495,
    "Asselineau": 2807.5738,
    "Fillon": 17793.6904,
    "Cheminade": 355.3163,
    "Lasalle": 434.5213,
    "(Mélenchon|Melenchon)": 3861.5755,
    "(Marine Le Pen)": 2583.6759,
    "entity:/m/0h3t838": 504.4341,
    "entity:/m/0f6b18": 1044.7095,
    "Poutou": 505.319,
    "abbreviation": "NQ",
    "max": 4,
    "second": 2,
    "third": 1,
    "maxname": "François Fillon",
    "image": "https://github.com/GoogleTrends/visualassets/blob/master/France_left_primaries/hamon.png?raw=true",
    "secondname": "Emmanuel Macron",
    "thirdname": "Benoît Hamon",
    "title": "Les candidats les plus recherchés",
    "subtitle": "(Dernière mise à jour le 16/03 à 22h)"
  },
  {
    "Region": "Pays de la Loire",
    "Hamon": 4602.1402,
    "Macron": 16033.1959,
    "Asselineau": 2681.4862,
    "Fillon": 20129.0319,
    "Cheminade": 319.1918,
    "Lasalle": 666.588,
    "(Mélenchon|Melenchon)": 3424.4325,
    "(Marine Le Pen)": 2533.5848,
    "entity:/m/0h3t838": 521.4383,
    "entity:/m/0f6b18": 996.7864,
    "Poutou": 390.7348,
    "abbreviation": "PL",
    "max": 4,
    "second": 2,
    "third": 1,
    "maxname": "François Fillon",
    "image": "https://github.com/GoogleTrends/visualassets/blob/master/France_left_primaries/hamon.png?raw=true",
    "secondname": "Emmanuel Macron",
    "thirdname": "Benoît Hamon",
    "title": "Les candidats les plus recherchés",
    "subtitle": "(Dernière mise à jour le 16/03 à 22h)"
  },
  {
    "Region": "PACA",
    "Hamon": 3657.9254,
    "Macron": 16218.6978,
    "Asselineau": 2511.3901,
    "Fillon": 17405.8396,
    "Cheminade": 300.4878,
    "Lasalle": 510.6859,
    "(Mélenchon|Melenchon)": 3615.8858,
    "(Marine Le Pen)": 3538.9724,
    "entity:/m/0h3t838": 390.7775,
    "entity:/m/0f6b18": 1001.3075,
    "Poutou": 320.5522,
    "abbreviation": "PR",
    "max": 4,
    "second": 2,
    "third": 1,
    "maxname": "François Fillon",
    "image": "https://github.com/GoogleTrends/visualassets/blob/master/France_left_primaries/hamon.png?raw=true",
    "secondname": "Emmanuel Macron",
    "thirdname": "Benoît Hamon",
    "title": "Les candidats les plus recherchés",
    "subtitle": "(Dernière mise à jour le 16/03 à 22h)"
  },
  {
    "Region": "Normandie",
    "Hamon": 4198.5682,
    "Macron": 14651.1382,
    "Asselineau": 2436.8895,
    "Fillon": 17208.9356,
    "Cheminade": 306.527,
    "Lasalle": 633.4891,
    "(Mélenchon|Melenchon)": 3606.8008,
    "(Marine Le Pen)": 2741.7136,
    "entity:/m/0h3t838": 536.4222,
    "entity:/m/0f6b18": 998.7671,
    "Poutou": 389.119,
    "abbreviation": "NO",
    "max": 4,
    "second": 2,
    "third": 1,
    "maxname": "François Fillon",
    "image": "https://github.com/GoogleTrends/visualassets/blob/master/France_left_primaries/hamon.png?raw=true",
    "secondname": "Emmanuel Macron",
    "thirdname": "Benoît Hamon",
    "title": "Les candidats les plus recherchés",
    "subtitle": "(Dernière mise à jour le 16/03 à 22h)"
  },
  {
    "Region": "Occitanie",
    "Hamon": 4185.2441,
    "Macron": 16120.3199,
    "Asselineau": 2725.3323,
    "Fillon": 16519.9264,
    "Cheminade": 306.8553,
    "Lasalle": 650.4841,
    "(Mélenchon|Melenchon)": 4576.2701,
    "(Marine Le Pen)": 2921.0495,
    "entity:/m/0h3t838": 460.4872,
    "entity:/m/0f6b18": 987.5754,
    "Poutou": 407.3698,
    "abbreviation": "OC",
    "max": 4,
    "second": 2,
    "third": 7,
    "maxname": "François Fillon",
    "image": "https://github.com/GoogleTrends/visualassets/blob/master/France_left_primaries/hamon.png?raw=true",
    "secondname": "Emmanuel Macron",
    "thirdname": "Jean Luc Melenchon",
    "title": "Les candidats les plus recherchés",
    "subtitle": "(Dernière mise à jour le 16/03 à 22h)"
  },
  {
    "Region": "Auvergne-Rhône-Alpes",
    "Hamon": 3932.2371,
    "Macron": 15708.7918,
    "Asselineau": 2719.7192,
    "Fillon": 16708.1041,
    "Cheminade": 299.7937,
    "Lasalle": 514.4187,
    "(Mélenchon|Melenchon)": 3735.2136,
    "(Marine Le Pen)": 2626.8854,
    "entity:/m/0h3t838": 467.5759,
    "entity:/m/0f6b18": 989.0921,
    "Poutou": 442.0254,
    "abbreviation": "AR",
    "max": 4,
    "second": 2,
    "third": 1,
    "maxname": "François Fillon",
    "image": "https://github.com/GoogleTrends/visualassets/blob/master/France_left_primaries/hamon.png?raw=true",
    "secondname": "Emmanuel Macron",
    "thirdname": "Benoît Hamon",
    "title": "Les candidats les plus recherchés",
    "subtitle": "(Dernière mise à jour le 16/03 à 22h)"
  }
]
