[
  {
    "Region": "Guyane",
    "Hamon": 2429.9803,
    "Valls": 560.7647,
    "Melenchon": 1074.799,
    "abbreviation": "GF",
    "max": 1,
    "second": 3,
    "third": 2,
    "maxname": "Benoît Hamon",
    "image": "https://github.com/GoogleTrends/visualassets/blob/master/France_left_primaries/hamon.png?raw=true",
    "secondname": "Jean-Luc Melenchon",
    "thirdname": "Manuel Valls"
  },
  {
    "Region": "Martinique",
    "Hamon": 5104.3285,
    "Valls": 760.4051,
    "Melenchon": 777.8857,
    "abbreviation": "MQ",
    "max": 1,
    "second": 3,
    "third": 2,
    "maxname": "Benoît Hamon",
    "image": "https://github.com/GoogleTrends/visualassets/blob/master/France_left_primaries/hamon.png?raw=true",
    "secondname": "Jean-Luc Melenchon",
    "thirdname": "Manuel Valls"
  },
  {
    "Region": "Guadeloupe",
    "Hamon": 4885.708,
    "Valls": 678.3588,
    "Melenchon": 891.7751,
    "abbreviation": "GP",
    "max": 1,
    "second": 3,
    "third": 2,
    "maxname": "Benoît Hamon",
    "image": "https://github.com/GoogleTrends/visualassets/blob/master/France_left_primaries/hamon.png?raw=true",
    "secondname": "Jean-Luc Melenchon",
    "thirdname": "Manuel Valls"
  },
  {
    "Region": "Mayotte",
    "Hamon": 2153.0495,
    "Valls": 161.4787,
    "Melenchon": 699.7411,
    "abbreviation": "MT",
    "max": 1,
    "second": 3,
    "third": 2,
    "maxname": "Benoît Hamon",
    "image": "https://github.com/GoogleTrends/visualassets/blob/master/France_left_primaries/hamon.png?raw=true",
    "secondname": "Jean-Luc Melenchon",
    "thirdname": "Manuel Valls"
  },
  {
    "Region": "Réunion",
    "Hamon": 2175.208,
    "Valls": 389.0276,
    "Melenchon": 1510.0963,
    "abbreviation": "RE",
    "max": 1,
    "second": 3,
    "third": 2,
    "maxname": "Benoît Hamon",
    "image": "https://github.com/GoogleTrends/visualassets/blob/master/France_left_primaries/hamon.png?raw=true",
    "secondname": "Jean-Luc Melenchon",
    "thirdname": "Manuel Valls"
  },
  {
    "Region": "Auvergne-Rhône-Alpes",
    "Hamon": 4138.2611,
    "Valls": 684.1637,
    "Melenchon": 1422.6832,
    "abbreviation": "AR",
    "max": 1,
    "second": 3,
    "third": 2,
    "maxname": "Benoît Hamon",
    "image": "https://github.com/GoogleTrends/visualassets/blob/master/France_left_primaries/hamon.png?raw=true",
    "secondname": "Jean-Luc Melenchon",
    "thirdname": "Manuel Valls"
  },
  {
    "Region": "Bourgogne-Franche-Comté",
    "Hamon": 3758.9822,
    "Valls": 624.4463,
    "Melenchon": 1475.4979,
    "abbreviation": "BF",
    "max": 1,
    "second": 3,
    "third": 2,
    "maxname": "Benoît Hamon",
    "image": "https://github.com/GoogleTrends/visualassets/blob/master/France_left_primaries/hamon.png?raw=true",
    "secondname": "Jean-Luc Melenchon",
    "thirdname": "Manuel Valls"
  },
  {
    "Region": "Bretagne",
    "Hamon": 6090.4907,
    "Valls": 803.9629,
    "Melenchon": 1579.9947,
    "abbreviation": "BT",
    "max": 1,
    "second": 3,
    "third": 2,
    "maxname": "Benoît Hamon",
    "image": "https://github.com/GoogleTrends/visualassets/blob/master/France_left_primaries/hamon.png?raw=true",
    "secondname": "Jean-Luc Melenchon",
    "thirdname": "Manuel Valls"
  },
  {
    "Region": "Centre-Val de Loire",
    "Hamon": 3693.3275,
    "Valls": 641.3757,
    "Melenchon": 1151.6595,
    "abbreviation": "CV",
    "max": 1,
    "second": 3,
    "third": 2,
    "maxname": "Benoît Hamon",
    "image": "https://github.com/GoogleTrends/visualassets/blob/master/France_left_primaries/hamon.png?raw=true",
    "secondname": "Jean-Luc Melenchon",
    "thirdname": "Manuel Valls"
  },
  {
    "Region": "Corse",
    "Hamon": 3794.1102,
    "Valls": 646.833,
    "Melenchon": 1351.5914,
    "abbreviation": "CE",
    "max": 1,
    "second": 3,
    "third": 2,
    "maxname": "Benoît Hamon",
    "image": "https://github.com/GoogleTrends/visualassets/blob/master/France_left_primaries/hamon.png?raw=true",
    "secondname": "Jean-Luc Melenchon",
    "thirdname": "Manuel Valls"
  },
  {
    "Region": "Grand Est",
    "Hamon": 3220.5431,
    "Valls": 554.2463,
    "Melenchon": 1099.907,
    "abbreviation": "GE",
    "max": 1,
    "second": 3,
    "third": 2,
    "maxname": "Benoît Hamon",
    "image": "https://github.com/GoogleTrends/visualassets/blob/master/France_left_primaries/hamon.png?raw=true",
    "secondname": "Jean-Luc Melenchon",
    "thirdname": "Manuel Valls"
  },
  {
    "Region": "Hauts-de-France",
    "Hamon": 3000.9968,
    "Valls": 593.2052,
    "Melenchon": 1072.4322,
    "abbreviation": "HF",
    "max": 1,
    "second": 3,
    "third": 2,
    "maxname": "Benoît Hamon",
    "image": "https://github.com/GoogleTrends/visualassets/blob/master/France_left_primaries/hamon.png?raw=true",
    "secondname": "Jean-Luc Melenchon",
    "thirdname": "Manuel Valls"
  },
  {
    "Region": "Île-de-France",
    "Hamon": 5418.3231,
    "Valls": 1129.3741,
    "Melenchon": 1541.7293,
    "abbreviation": "IF",
    "max": 1,
    "second": 3,
    "third": 2,
    "maxname": "Benoît Hamon",
    "image": "https://github.com/GoogleTrends/visualassets/blob/master/France_left_primaries/hamon.png?raw=true",
    "secondname": "Jean-Luc Melenchon",
    "thirdname": "Manuel Valls"
  },
  {
    "Region": "Nouvelle-Aquitaine",
    "Hamon": 4345.6143,
    "Valls": 695.2463,
    "Melenchon": 1524.3438,
    "abbreviation": "NQ",
    "max": 1,
    "second": 3,
    "third": 2,
    "maxname": "Benoît Hamon",
    "image": "https://github.com/GoogleTrends/visualassets/blob/master/France_left_primaries/hamon.png?raw=true",
    "secondname": "Jean-Luc Melenchon",
    "thirdname": "Manuel Valls"
  },
  {
    "Region": "Pays de la Loire",
    "Hamon": 4883.6144,
    "Valls": 612.5507,
    "Melenchon": 1257.341,
    "abbreviation": "PL",
    "max": 1,
    "second": 3,
    "third": 2,
    "maxname": "Benoît Hamon",
    "image": "https://github.com/GoogleTrends/visualassets/blob/master/France_left_primaries/hamon.png?raw=true",
    "secondname": "Jean-Luc Melenchon",
    "thirdname": "Manuel Valls"
  },
  {
    "Region": "PACA",
    "Hamon": 3705.0739,
    "Valls": 683.1215,
    "Melenchon": 1461.9461,
    "abbreviation": "PR",
    "max": 1,
    "second": 3,
    "third": 2,
    "maxname": "Benoît Hamon",
    "image": "https://github.com/GoogleTrends/visualassets/blob/master/France_left_primaries/hamon.png?raw=true",
    "secondname": "Jean-Luc Melenchon",
    "thirdname": "Manuel Valls"
  },
  {
    "Region": "Normandie",
    "Hamon": 4458.9498,
    "Valls": 602.0907,
    "Melenchon": 1276.2336,
    "abbreviation": "NO",
    "max": 1,
    "second": 3,
    "third": 2,
    "maxname": "Benoît Hamon",
    "image": "https://github.com/GoogleTrends/visualassets/blob/master/France_left_primaries/hamon.png?raw=true",
    "secondname": "Jean-Luc Melenchon",
    "thirdname": "Manuel Valls"
  },
  {
    "Region": "Occitanie",
    "Hamon": 4402.0504,
    "Valls": 798.8462,
    "Melenchon": 1781.2111,
    "abbreviation": "OC",
    "max": 1,
    "second": 3,
    "third": 2,
    "maxname": "Benoît Hamon",
    "image": "https://github.com/GoogleTrends/visualassets/blob/master/France_left_primaries/hamon.png?raw=true",
    "secondname": "Jean-Luc Melenchon",
    "thirdname": "Manuel Valls"
  },
  {
    "Region": "Auvergne-Rhône-Alpes",
    "Hamon": 4138.2611,
    "Valls": 684.1637,
    "Melenchon": 1422.6832,
    "abbreviation": "AR",
    "max": 1,
    "second": 3,
    "third": 2,
    "maxname": "Benoît Hamon",
    "image": "https://github.com/GoogleTrends/visualassets/blob/master/France_left_primaries/hamon.png?raw=true",
    "secondname": "Jean-Luc Melenchon",
    "thirdname": "Manuel Valls"
  }
]
