[
  {
    "Region": "Guyane",
    "Hamon": 2293.7605,
    "Valls": 561.7373,
    "Melenchon": 1100.0688,
    "abbreviation": "GF",
    "max": 1,
    "second": 3,
    "third": 2,
    "maxname": "Benoît Hamon",
    "image": "https://github.com/GoogleTrends/visualassets/blob/master/France_left_primaries/hamon.png?raw=true",
    "secondname": "Jean-Luc Melenchon",
    "thirdname": "Manuel Valls"
  },
  {
    "Region": "Martinique",
    "Hamon": 5066.6053,
    "Valls": 778.8046,
    "Melenchon": 787.5552,
    "abbreviation": "MQ",
    "max": 1,
    "second": 3,
    "third": 2,
    "maxname": "Benoît Hamon",
    "image": "https://github.com/GoogleTrends/visualassets/blob/master/France_left_primaries/hamon.png?raw=true",
    "secondname": "Jean-Luc Melenchon",
    "thirdname": "Manuel Valls"
  },
  {
    "Region": "Guadeloupe",
    "Hamon": 4783.4005,
    "Valls": 678.9835,
    "Melenchon": 884.9672,
    "abbreviation": "GP",
    "max": 1,
    "second": 3,
    "third": 2,
    "maxname": "Benoît Hamon",
    "image": "https://github.com/GoogleTrends/visualassets/blob/master/France_left_primaries/hamon.png?raw=true",
    "secondname": "Jean-Luc Melenchon",
    "thirdname": "Manuel Valls"
  },
  {
    "Region": "Mayotte",
    "Hamon": 2111.8752,
    "Valls": 162.4519,
    "Melenchon": 758.1091,
    "abbreviation": "MT",
    "max": 1,
    "second": 3,
    "third": 2,
    "maxname": "Benoît Hamon",
    "image": "https://github.com/GoogleTrends/visualassets/blob/master/France_left_primaries/hamon.png?raw=true",
    "secondname": "Jean-Luc Melenchon",
    "thirdname": "Manuel Valls"
  },
  {
    "Region": "Réunion",
    "Hamon": 2211.6276,
    "Valls": 427.2462,
    "Melenchon": 1549.8148,
    "abbreviation": "RE",
    "max": 1,
    "second": 3,
    "third": 2,
    "maxname": "Benoît Hamon",
    "image": "https://github.com/GoogleTrends/visualassets/blob/master/France_left_primaries/hamon.png?raw=true",
    "secondname": "Jean-Luc Melenchon",
    "thirdname": "Manuel Valls"
  },
  {
    "Region": "Auvergne-Rhône-Alpes",
    "Hamon": 4068.3306,
    "Valls": 719.4305,
    "Melenchon": 1455.2812,
    "abbreviation": "AR",
    "max": 1,
    "second": 3,
    "third": 2,
    "maxname": "Benoît Hamon",
    "image": "https://github.com/GoogleTrends/visualassets/blob/master/France_left_primaries/hamon.png?raw=true",
    "secondname": "Jean-Luc Melenchon",
    "thirdname": "Manuel Valls"
  },
  {
    "Region": "Bourgogne-Franche-Comté",
    "Hamon": 3702.2456,
    "Valls": 652.7318,
    "Melenchon": 1483.575,
    "abbreviation": "BF",
    "max": 1,
    "second": 3,
    "third": 2,
    "maxname": "Benoît Hamon",
    "image": "https://github.com/GoogleTrends/visualassets/blob/master/France_left_primaries/hamon.png?raw=true",
    "secondname": "Jean-Luc Melenchon",
    "thirdname": "Manuel Valls"
  },
  {
    "Region": "Bretagne",
    "Hamon": 6028.7515,
    "Valls": 844.8125,
    "Melenchon": 1607.8689,
    "abbreviation": "BT",
    "max": 1,
    "second": 3,
    "third": 2,
    "maxname": "Benoît Hamon",
    "image": "https://github.com/GoogleTrends/visualassets/blob/master/France_left_primaries/hamon.png?raw=true",
    "secondname": "Jean-Luc Melenchon",
    "thirdname": "Manuel Valls"
  },
  {
    "Region": "Centre-Val de Loire",
    "Hamon": 3626.3564,
    "Valls": 661.8073,
    "Melenchon": 1175.8219,
    "abbreviation": "CV",
    "max": 1,
    "second": 3,
    "third": 2,
    "maxname": "Benoît Hamon",
    "image": "https://github.com/GoogleTrends/visualassets/blob/master/France_left_primaries/hamon.png?raw=true",
    "secondname": "Jean-Luc Melenchon",
    "thirdname": "Manuel Valls"
  },
  {
    "Region": "Corse",
    "Hamon": 3787.7983,
    "Valls": 657.067,
    "Melenchon": 1410.7616,
    "abbreviation": "CE",
    "max": 1,
    "second": 3,
    "third": 2,
    "maxname": "Benoît Hamon",
    "image": "https://github.com/GoogleTrends/visualassets/blob/master/France_left_primaries/hamon.png?raw=true",
    "secondname": "Jean-Luc Melenchon",
    "thirdname": "Manuel Valls"
  },
  {
    "Region": "Grand Est",
    "Hamon": 3171.9074,
    "Valls": 580.11,
    "Melenchon": 1114.6742,
    "abbreviation": "GE",
    "max": 1,
    "second": 3,
    "third": 2,
    "maxname": "Benoît Hamon",
    "image": "https://github.com/GoogleTrends/visualassets/blob/master/France_left_primaries/hamon.png?raw=true",
    "secondname": "Jean-Luc Melenchon",
    "thirdname": "Manuel Valls"
  },
  {
    "Region": "Hauts-de-France",
    "Hamon": 2975.5079,
    "Valls": 625.5082,
    "Melenchon": 1093.3363,
    "abbreviation": "HF",
    "max": 1,
    "second": 3,
    "third": 2,
    "maxname": "Benoît Hamon",
    "image": "https://github.com/GoogleTrends/visualassets/blob/master/France_left_primaries/hamon.png?raw=true",
    "secondname": "Jean-Luc Melenchon",
    "thirdname": "Manuel Valls"
  },
  {
    "Region": "Île-de-France",
    "Hamon": 5337.9176,
    "Valls": 1193.2691,
    "Melenchon": 1586.9914,
    "abbreviation": "IF",
    "max": 1,
    "second": 3,
    "third": 2,
    "maxname": "Benoît Hamon",
    "image": "https://github.com/GoogleTrends/visualassets/blob/master/France_left_primaries/hamon.png?raw=true",
    "secondname": "Jean-Luc Melenchon",
    "thirdname": "Manuel Valls"
  },
  {
    "Region": "Nouvelle-Aquitaine",
    "Hamon": 4259.3509,
    "Valls": 725.6801,
    "Melenchon": 1550.0005,
    "abbreviation": "NQ",
    "max": 1,
    "second": 3,
    "third": 2,
    "maxname": "Benoît Hamon",
    "image": "https://github.com/GoogleTrends/visualassets/blob/master/France_left_primaries/hamon.png?raw=true",
    "secondname": "Jean-Luc Melenchon",
    "thirdname": "Manuel Valls"
  },
  {
    "Region": "Pays de la Loire",
    "Hamon": 4843.3686,
    "Valls": 641.0242,
    "Melenchon": 1282.0483,
    "abbreviation": "PL",
    "max": 1,
    "second": 3,
    "third": 2,
    "maxname": "Benoît Hamon",
    "image": "https://github.com/GoogleTrends/visualassets/blob/master/France_left_primaries/hamon.png?raw=true",
    "secondname": "Jean-Luc Melenchon",
    "thirdname": "Manuel Valls"
  },
  {
    "Region": "PACA",
    "Hamon": 3649.1726,
    "Valls": 716.9029,
    "Melenchon": 1481.9454,
    "abbreviation": "PR",
    "max": 1,
    "second": 3,
    "third": 2,
    "maxname": "Benoît Hamon",
    "image": "https://github.com/GoogleTrends/visualassets/blob/master/France_left_primaries/hamon.png?raw=true",
    "secondname": "Jean-Luc Melenchon",
    "thirdname": "Manuel Valls"
  },
  {
    "Region": "Normandie",
    "Hamon": 4397.5388,
    "Valls": 636.6388,
    "Melenchon": 1300.6688,
    "abbreviation": "NO",
    "max": 1,
    "second": 3,
    "third": 2,
    "maxname": "Benoît Hamon",
    "image": "https://github.com/GoogleTrends/visualassets/blob/master/France_left_primaries/hamon.png?raw=true",
    "secondname": "Jean-Luc Melenchon",
    "thirdname": "Manuel Valls"
  },
  {
    "Region": "Occitanie",
    "Hamon": 4342.5068,
    "Valls": 833.7549,
    "Melenchon": 1816.3659,
    "abbreviation": "OC",
    "max": 1,
    "second": 3,
    "third": 2,
    "maxname": "Benoît Hamon",
    "image": "https://github.com/GoogleTrends/visualassets/blob/master/France_left_primaries/hamon.png?raw=true",
    "secondname": "Jean-Luc Melenchon",
    "thirdname": "Manuel Valls"
  },
  {
    "Region": "Auvergne-Rhône-Alpes",
    "Hamon": 4068.3306,
    "Valls": 719.4305,
    "Melenchon": 1455.2812,
    "abbreviation": "AR",
    "max": 1,
    "second": 3,
    "third": 2,
    "maxname": "Benoît Hamon",
    "image": "https://github.com/GoogleTrends/visualassets/blob/master/France_left_primaries/hamon.png?raw=true",
    "secondname": "Jean-Luc Melenchon",
    "thirdname": "Manuel Valls"
  }
]
